odoo/addons/l10n_cl_product/README.rst
odoo/addons/l10n_cl_product/__init__.py
odoo/addons/l10n_cl_product/__manifest__.py
odoo/addons/l10n_cl_product/i18n/l10n_cl_product.pot
odoo/addons/l10n_cl_product/models/__init__.py
odoo/addons/l10n_cl_product/models/product_template.py
odoo/addons/l10n_cl_product/readme/CONTRIBUTORS.rst
odoo/addons/l10n_cl_product/readme/DESCRIPTION.rst
odoo/addons/l10n_cl_product/readme/USAGE.rst
odoo/addons/l10n_cl_product/static/description/icon.png
odoo/addons/l10n_cl_product/static/description/index.html
odoo/addons/l10n_cl_product/views/product_template.xml
odoo12_addon_l10n_cl_product-12.0.1.0.0.99.dev4.dist-info/METADATA
odoo12_addon_l10n_cl_product-12.0.1.0.0.99.dev4.dist-info/WHEEL
odoo12_addon_l10n_cl_product-12.0.1.0.0.99.dev4.dist-info/top_level.txt
odoo12_addon_l10n_cl_product-12.0.1.0.0.99.dev4.dist-info/RECORD
